skald/__init__.py
skald/cli.py
skald/collector.py
skald/core.py
skald/decorators.py
skald/emitter.py
skald/monitor.py
skald/scheduler.py
skald/export/__init__.py
skald/export/parquet.py
skald/redaction/__init__.py
skald/redaction/base.py
skald/redaction/default.py
skald/schema/__init__.py
skald/schema/models.py
skald/storage/__init__.py
skald/storage/base.py
skald/storage/mock.py
skald/storage/sqlite.py
skald/transport/__init__.py
skald/transport/base.py
skald/transport/stdio.py
skald/transport/tcp.py
sibylline_skald-0.2.0.dist-info/METADATA
sibylline_skald-0.2.0.dist-info/WHEEL
sibylline_skald-0.2.0.dist-info/entry_points.txt
sibylline_skald-0.2.0.dist-info/licenses/LICENSE
sibylline_skald-0.2.0.dist-info/RECORD
