Metadata-Version: 2.4
Name: sibylline-skald
Version: 0.2.0
Summary: Universal Execution Monitoring & Feedback Library for Python applications, supporting MCP servers, functions, shell commands, and more
Project-URL: Homepage, https://github.com/sibyllinesoft/skald
Project-URL: Repository, https://github.com/sibyllinesoft/skald.git
Project-URL: Documentation, https://github.com/sibyllinesoft/skald#readme
Project-URL: Issues, https://github.com/sibyllinesoft/skald/issues
Author-email: Nathan Rice <nathan.alexander.rice@gmail.com>
License: MIT
License-File: LICENSE
Keywords: agent,ai,feedback,mcp,tools
Classifier: Development Status :: 3 - Alpha
Classifier: Intended Audience :: Developers
Classifier: License :: OSI Approved :: MIT License
Classifier: Programming Language :: Python :: 3
Classifier: Programming Language :: Python :: 3.9
Classifier: Programming Language :: Python :: 3.10
Classifier: Programming Language :: Python :: 3.11
Classifier: Programming Language :: Python :: 3.12
Classifier: Topic :: Software Development :: Libraries :: Python Modules
Classifier: Topic :: System :: Networking
Requires-Python: >=3.9
Requires-Dist: aiohttp>=3.9.0
Requires-Dist: aiosqlite>=0.19.0
Requires-Dist: asyncio-mqtt>=0.16.0
Requires-Dist: click>=8.1.0
Requires-Dist: fastapi>=0.104.0
Requires-Dist: fastparquet>=2024.2.0
Requires-Dist: psutil>=5.9.0
Requires-Dist: pyarrow>=15.0.0
Requires-Dist: pydantic>=2.5.0
Requires-Dist: structlog>=23.2.0
Requires-Dist: uvicorn>=0.24.0
Requires-Dist: uvloop>=0.19.0; sys_platform != 'win32'
Provides-Extra: dev
Requires-Dist: black>=24.0.0; extra == 'dev'
Requires-Dist: isort>=5.13.0; extra == 'dev'
Requires-Dist: mypy>=1.8.0; extra == 'dev'
Requires-Dist: pytest-asyncio>=0.23.0; extra == 'dev'
Requires-Dist: pytest-cov>=4.1.0; extra == 'dev'
Requires-Dist: pytest>=8.0.0; extra == 'dev'
Requires-Dist: ruff>=0.3.0; extra == 'dev'
Provides-Extra: docs
Requires-Dist: myst-parser>=2.0.0; extra == 'docs'
Requires-Dist: sphinx-rtd-theme>=2.0.0; extra == 'docs'
Requires-Dist: sphinx>=7.2.0; extra == 'docs'
Provides-Extra: test
Requires-Dist: hypothesis>=6.98.0; extra == 'test'
Requires-Dist: pytest-asyncio>=0.23.0; extra == 'test'
Requires-Dist: pytest-cov>=4.1.0; extra == 'test'
Requires-Dist: pytest>=8.0.0; extra == 'test'
